{
  "projects": [
    {
      "id": "1",
      "title": "Create new landing page Again!!!!",
      "details": "Lorem ipsum Lorem ipsumLorem ipsum Lorem ipsum Lorem ipsum",
      "complete": true
    },
    {
      "id": "2",
      "title": "Create new landing page",
      "details": "Lorem ipsum",
      "complete": true
    },
    {
      "id": "3",
      "title": "Create new landing page",
      "details": "Lorem ipsum",
      "complete": true
    },
    {
      "id": "4",
      "title": "Create new landing page",
      "details": "Lorem ipsum",
      "complete": true
    },
    {
      "id": "5",
      "title": "Create new landing page",
      "details": "Lorem ipsum",
      "complete": false
    },
    {
      "id": "f210",
      "title": "Create a dashboard Admin",
      "details": "hi"
    },
    {
      "id": "0497",
      "title": "landing page",
      "details": "blah blah blah",
      "complete": false
    },
    {
      "id": "bd64",
      "title": "My Lucky Page",
      "details": "blah blah blah Lorem Ipsum",
      "complete": false
    },
    {
      "id": "c43a",
      "title": "Mera Baba",
      "details": "Blah blah blah",
      "complete": false
    }
  ]
}